eventsourcing_mongodb/__init__.py
eventsourcing_mongodb/datastore.py
eventsourcing_mongodb/factory.py
eventsourcing_mongodb/recorders/__init__.py
eventsourcing_mongodb/recorders/aggregate.py
eventsourcing_mongodb/recorders/application.py
eventsourcing_mongodb/recorders/process.py
eventsourcing_mongodb-4.0.3.dist-info/LICENSE
eventsourcing_mongodb-4.0.3.dist-info/METADATA
eventsourcing_mongodb-4.0.3.dist-info/WHEEL
eventsourcing_mongodb-4.0.3.dist-info/top_level.txt
eventsourcing_mongodb-4.0.3.dist-info/RECORD
