Metadata-Version: 2.1
Name: eventsourcing-mongodb
Version: 4.0.3
Summary: An extension package for the Python Eventsourcing library that provides a persistence module for MongoDB.
Author: Luxaaa
License: MIT License
Project-URL: Repository, https://github.com/Luxaaa/eventsourcing-mongodb
Keywords: eventsourcing,mongodb
Classifier: License :: OSI Approved :: MIT License
Classifier: Programming Language :: Python
Classifier: Programming Language :: Python :: 3
Requires-Python: >=3.7
License-File: LICENSE
Requires-Dist: eventsourcing >=9.2.6
Requires-Dist: pymongo >=4.1.1
Provides-Extra: dev
